gzstv/__init__.py
gzstv/attentions.py
gzstv/commons.py
gzstv/mel_processing.py
gzstv/models.py
gzstv/modules.py
gzstv/rsa.json
gzstv/transforms.py
gzstv/utils.py
gzstv/text/__init__.py
gzstv/text/cleaners.py
gzstv/text/symbols.py
rsatv/__init__.py
rsatv/attentions.py
rsatv/commons.py
rsatv/mel_processing.py
rsatv/models.py
rsatv/modules.py
rsatv/transforms.py
rsatv/utils.py
rsatv/text/__init__.py
rsatv/text/cleaners.py
rsatv/text/symbols.py
gzstv-0.0.8.dist-info/LICENSE
gzstv-0.0.8.dist-info/METADATA
gzstv-0.0.8.dist-info/WHEEL
gzstv-0.0.8.dist-info/top_level.txt
gzstv-0.0.8.dist-info/RECORD
