Metadata-Version: 2.1
Name: gzstv
Version: 0.0.8
Summary: GZS-TV: A Generalizable zero-shot speaker adaptive text-to-speech and voice conversion model
Home-page: https://github.com/mushanshanshan/gzs_tv
Author: Mushan
License: CC BY-NC 4.0
Keywords: None
Platform: UNKNOWN
Classifier: Environment :: Console
Classifier: License :: Free For Educational Use
Classifier: Programming Language :: Python :: 3.7
Classifier: Operating System :: POSIX :: Linux
License-File: LICENSE
Requires-Dist: Cython
Requires-Dist: gdown
Requires-Dist: torch
Requires-Dist: librosa (==0.9.1)
Requires-Dist: numpy
Requires-Dist: phonemizer (==3.1.1)
Requires-Dist: scipy (==1.5.0)
Requires-Dist: Unidecode
Requires-Dist: vits-monotonic-align
